frozen/__init__.py
frozen/workflow.py
frozen/basis/__init__.py
frozen/basis/constant.py
frozen/basis/yamler.py
frozen_quant-3.2.2.dist-info/METADATA
frozen_quant-3.2.2.dist-info/WHEEL
frozen_quant-3.2.2.dist-info/entry_points.txt
frozen_quant-3.2.2.dist-info/top_level.txt
frozen_quant-3.2.2.dist-info/RECORD
