Metadata-Version: 2.1
Name: frozen-quant
Version: 3.2.2
Summary: A Quantitative Backtest Framework
Home-page: https://github.com/Mxyzptlk-Z/frozen
Author: lig
Author-email: legendarylig@gmail.com
License: MIT Licence
Classifier: Operating System :: POSIX :: Linux
Classifier: Operating System :: Microsoft :: Windows
Classifier: Operating System :: MacOS
Classifier: License :: OSI Approved :: MIT License
Classifier: Natural Language :: English
Classifier: Intended Audience :: Developers
Classifier: Intended Audience :: End Users/Desktop
Classifier: Development Status :: 3 - Alpha
Classifier: Programming Language :: Python
Classifier: Programming Language :: Python :: 3
Classifier: Programming Language :: Python :: 3.9
Classifier: Programming Language :: Python :: 3.10
Classifier: Programming Language :: Python :: 3.11
Classifier: Topic :: Software Development :: Libraries :: Python Modules
Requires-Python: >=3.10.0
Requires-Dist: numpy<1.24,>=1.20.0
Requires-Dist: pandas>=1.5.3
Requires-Dist: scipy>=1.11.4
Requires-Dist: statsmodels>=0.14.1
Requires-Dist: matplotlib>=3.7.1
Requires-Dist: calplot==0.1.7.5
Requires-Dist: joypy==0.2.6
Requires-Dist: mpld3==0.5.10
Requires-Dist: pyyaml>=6.0.1
Requires-Dist: nltk>=3.8.1
Requires-Dist: openpyxl>=3.1.2
Requires-Dist: dill>=0.3.9
Requires-Dist: tqdm>=4.66.1
Requires-Dist: joblib>=1.2.0
Requires-Dist: tqdm-joblib==0.0.3
Requires-Dist: numba>=0.59.0
Requires-Dist: pymongo>=4.6.1
Requires-Dist: duckdb>=0.10.2
Requires-Dist: chdb>=2.0.4
Requires-Dist: empyrical==0.4.1
Requires-Dist: scikit-learn>=1.2.2
Requires-Dist: chinese-calendar>=1.9.0
Requires-Dist: holidays>=0.41
Requires-Dist: pandas-market-calendars>=4.3.3
Requires-Dist: pdpipe>=0.3.2
Requires-Dist: quantstats>=0.0.62
Requires-Dist: tushare>=1.3.7
Requires-Dist: IPython==8.26.0
Requires-Dist: setuptools>=75.1.0
Requires-Dist: optuna>=4.0.0
Provides-Extra: dev
Requires-Dist: prefect>=3.0.3; extra == "dev"
Requires-Dist: streamlit>=1.30.0; extra == "dev"
Requires-Dist: mlflow; extra == "dev"
Requires-Dist: setuptools; extra == "dev"
Provides-Extra: rl
Requires-Dist: torch; extra == "rl"
